lesscode_encryption-0.0.3.dist-info/METADATA
lesscode_encryption-0.0.3.dist-info/WHEEL
lesscode_encryption-0.0.3.dist-info/licenses/LICENSE
lesscode_encryption/__init__.py
lesscode_encryption/lesscode_encryption.cpython-38-x86_64-linux-gnu.so
lesscode_encryption-0.0.3.dist-info/RECORD
