Metadata-Version: 2.3
Name: lesscode_encryption
Version: 0.0.3
Classifier: Programming Language :: Python :: 3
Classifier: Operating System :: OS Independent
Classifier: Programming Language :: Rust
Classifier: License :: OSI Approved :: MIT License
Classifier: Operating System :: OS Independent
License-File: LICENSE
Summary: lesscode_encryption是基于Rust语言开发的加密算法库
Author-email: navysummer <navysummer@yeah.net>
License: MIT
Requires-Python: >=3.7
